{"movies":
  [
    { "id": 1,
      "name": "Saving Private Ryan",
      "year": 1998,
      "description": "A group of U.S. soldiers go behind enemy lines to retrive a paratrooper whose brothers have been killed in action.",
      "image": "https://image.tmdb.org/t/p/w370_and_h556_bestv2/miDoEMlYDJhOCvxlzI0wZqBs9Yt.jpg"
    },
    { "id": 2,
      "name": "Raiders of the Lost Ark",
      "year": 1981,
      "description": "An archaeologist is hired by the U.S. government to find a gold-covered wooden chest before the Nazis.",
      "image": "https://image.tmdb.org/t/p/w370_and_h556_bestv2/44sKJOGP3fTm4QXBcIuqu0RkdP7.jpg"
    },
    { "id": 3,
      "name": "Raging Bull",
      "year": 1980,
      "description": "A violent-tempered boxer makes his way to the top and leaves his old life behind.",
      "image": "https://image.tmdb.org/t/p/w370_and_h556_bestv2/3cgzzWsUOBlNjmA5m4qs9BGkezC.jpg"
    },
    { "id": 4,
      "name": "Jurassic Park",
      "year": 1993,
      "description": "During a preview tour, a theme park suffers a major power breakdown and finds its cloned dinosaur exhibits have run amok.",
      "image": "https://image.tmdb.org/t/p/w370_and_h556_bestv2/c414cDeQ9b6qLPLeKmiJuLDUREJ.jpg"
    },
    { "id": 5,
      "name": "It's a Wonderful Life",
      "year": 1946,
      "description": "An angel is sent from Heaven to help a desperately frustrated businessman by showing him what life would have been like if he never existed.",
      "image": "https://image.tmdb.org/t/p/w370_and_h556_bestv2/rgj6QjdyCeDrO9KGt1kusGyhvb2.jpg"
    },
    { "id": 6,
      "name": "Gone With the Wind",
      "year": 1939,
      "description": "A manipulative women and a roguish man conduct a turbulent romance during the American Civil War and Reconstruction periods.",
      "image": "https://image.tmdb.org/t/p/w370_and_h556_bestv2/l7WYvM8iWvt7EoloaT4Yduz023g.jpg"
    },
    { "id": 7,
      "name": "Forrest Gump",
      "year": 1994,
      "description": "A simple man with a low IQ waits at a bus stop and shares life stories with strangers.",
      "image": "https://image.tmdb.org/t/p/w370_and_h556_bestv2/yE5d3BUhE8hCnkMUJOo1QDoOGNz.jpg"
    },
    { "id": 8,
      "name": "E.T. the Extra-Terrestrial",
      "year": 1982,
      "description": "A troubled child finds the courage to help a friendly alien escape Earth and return to his home world.",
      "image": "https://image.tmdb.org/t/p/w370_and_h556_bestv2/8htLKK03TJjKZOXJgihZCu8v0P.jpg"
    },
    { "id": 9,
      "name": "Bonnie and Clyde",
      "year": 1967,
      "description": "A bored waitress falls in love with an ex-con as they run across the country robbing banks together.",
      "image": "https://image.tmdb.org/t/p/w370_and_h556_bestv2/hmbuq4kPp3YNAbFEAdtNnYHnHtZ.jpg"
    },
    { "id": 10,
      "name": "Titanic",
      "year": 1997,
      "description": "A 17-year-old aristocrat falls in love with a kind, but poor, artist aboard in a luxurious, ill-fated ship.",
      "image": "https://image.tmdb.org/t/p/w370_and_h556_bestv2/kHXEpyfl6zqn8a6YuozZUujufXf.jpg"
    },
    { "id": 11,
      "name": "The Wizard of Oz",
      "year": 1939,
      "description": "A young woman is swept away in a tornado from a farm in Kansas to a magical land. ",
      "image": "https://image.tmdb.org/t/p/w370_and_h556_bestv2/tKEHoKPZv3af0Pn3poaOLHOJ6NM.jpg"
    },
    { "id": 12,
      "name": "The Sound of Music",
      "year": 1965,
      "description": "A woman leaves an Austrian convent to become a governess to the children of a naval officer widower.",
      "image": "https://image.tmdb.org/t/p/w370_and_h556_bestv2/459fPVvI4lkEV0piSfcq0irKHi8.jpg"
    }
  ]
}
